{
  "matches": [
    {
      "sport": "automovilismo",
      "date": {
        "hour": "09:00",
        "day": "26/11/2025",
        "zone": "Europe/Madrid"
      },
      "details": {
        "competition": "WRC Rally",
        "round": "Rally de Arabia Saudí"
      },
      "teams": {
        "local": {
          "name": null,
          "image": null
        },
        "visitor": {
          "name": null,
          "image": null
        }
      },
      "channels": [
        "DAZN",
        "DAZN App Gratis"
      ],
      "event": {},
      "eventType": "tournament"
    }
  ],
  "updated": "2025-11-26T00:12:48.476Z"
}