{
  "matches": [
    {
      "sport": "automovilismo",
      "date": {
        "hour": "06:55",
        "day": "07/06/2025",
        "zone": "Europe/Madrid"
      },
      "details": {
        "competition": "Supercars Championship",
        "round": "Wanneroo Raceway"
      },
      "teams": {
        "local": {
          "name": null,
          "image": null
        },
        "visitor": {
          "name": null,
          "image": null
        }
      },
      "channels": [
        "DAZN",
        "DAZN App Gratis"
      ],
      "event": {},
      "eventType": "tournament"
    },
    {
      "sport": "automovilismo",
      "date": {
        "hour": "09:05",
        "day": "07/06/2025",
        "zone": "Europe/Madrid"
      },
      "details": {
        "competition": "WRC Rally",
        "round": "Rally de Cerdeña"
      },
      "teams": {
        "local": {
          "name": null,
          "image": null
        },
        "visitor": {
          "name": null,
          "image": null
        }
      },
      "channels": [
        "DAZN"
      ],
      "event": {},
      "eventType": "tournament"
    },
    {
      "sport": "automovilismo",
      "date": {
        "hour": "10:10",
        "day": "07/06/2025",
        "zone": "Europe/Madrid"
      },
      "details": {
        "competition": null,
        "round": "Wanneroo Raceway"
      },
      "teams": {
        "local": {
          "name": null,
          "image": null
        },
        "visitor": {
          "name": null,
          "image": null
        }
      },
      "channels": [
        "DAZN",
        "DAZN App Gratis"
      ],
      "event": {},
      "eventType": "tournament"
    },
    {
      "sport": "automovilismo",
      "date": {
        "hour": "13:30",
        "day": "07/06/2025",
        "zone": "Europe/Madrid"
      },
      "details": {
        "competition": "DTM",
        "round": "Circuit Park Zandvoort"
      },
      "teams": {
        "local": {
          "name": null,
          "image": null
        },
        "visitor": {
          "name": null,
          "image": null
        }
      },
      "channels": [
        "DAZN",
        "DAZN App Gratis",
        "DAZN 2",
        "DAZN 2 Bar"
      ],
      "event": {},
      "eventType": "tournament"
    }
  ],
  "updated": "2025-06-07T00:12:21.377Z"
}