{
  "matches": [
    {
      "sport": "baloncesto",
      "date": {
        "hour": "01:00",
        "day": "16/10/2025",
        "zone": "Europe/Madrid"
      },
      "details": {
        "competition": "NBA Pretemporada",
        "round": null
      },
      "teams": {
        "local": {
          "name": "Charlotte Hornets",
          "image": "https://static.futbolenlatv.com/img/20141024124231-charlotte-hornets.webp"
        },
        "visitor": {
          "name": "Memphis Grizzlies",
          "image": "https://static.futbolenlatv.com/img/20191028090731-memphis-grizzlies.webp"
        }
      },
      "channels": [
        "NBA League Pass"
      ],
      "event": {},
      "eventType": "match"
    },
    {
      "sport": "baloncesto",
      "date": {
        "hour": "01:30",
        "day": "16/10/2025",
        "zone": "Europe/Madrid"
      },
      "details": {
        "competition": "NBA Pretemporada",
        "round": null
      },
      "teams": {
        "local": {
          "name": "Boston Celtics",
          "image": "https://static.futbolenlatv.com/img/20130808083552-boston-celtics.webp"
        },
        "visitor": {
          "name": "Toronto Raptors",
          "image": "https://static.futbolenlatv.com/img/20201220190859-toronto-raptors.webp"
        }
      },
      "channels": [
        "NBA League Pass"
      ],
      "event": {},
      "eventType": "match"
    },
    {
      "sport": "baloncesto",
      "date": {
        "hour": "04:00",
        "day": "16/10/2025",
        "zone": "Europe/Madrid"
      },
      "details": {
        "competition": "NBA Pretemporada",
        "round": null
      },
      "teams": {
        "local": {
          "name": "Sacramento Kings",
          "image": "https://static.futbolenlatv.com/img/20201220190924-sacramento-kings.webp"
        },
        "visitor": {
          "name": "Los Angeles Clippers",
          "image": "https://static.futbolenlatv.com/img/20191028090717-los-angeles-clippers.webp"
        }
      },
      "channels": [
        "NBA League Pass"
      ],
      "event": {},
      "eventType": "match"
    },
    {
      "sport": "baloncesto",
      "date": {
        "hour": "04:30",
        "day": "16/10/2025",
        "zone": "Europe/Madrid"
      },
      "details": {
        "competition": "NBA Pretemporada",
        "round": null
      },
      "teams": {
        "local": {
          "name": "Los Angeles Lakers",
          "image": "https://static.futbolenlatv.com/img/20130808083216-la-lakers.webp"
        },
        "visitor": {
          "name": "Dallas Mavericks",
          "image": "https://static.futbolenlatv.com/img/20130808083728-dallas-mavericks.webp"
        }
      },
      "channels": [
        "NBA League Pass"
      ],
      "event": {},
      "eventType": "match"
    },
    {
      "sport": "baloncesto",
      "date": {
        "hour": "18:00",
        "day": "16/10/2025",
        "zone": "Europe/Madrid"
      },
      "details": {
        "competition": "Eurocup Women",
        "round": "Liga Regular"
      },
      "teams": {
        "local": {
          "name": "BC Neptunas",
          "image": "https://static.futbolenlatv.com/img/20131006063854-bc-neptunas.webp"
        },
        "visitor": {
          "name": "Panathinaikos BC",
          "image": "https://static.futbolenlatv.com/img/20130716013710-panathinaikos-bc.webp"
        }
      },
      "channels": [
        "FIBA YouTube"
      ],
      "event": {},
      "eventType": "match"
    },
    {
      "sport": "baloncesto",
      "date": {
        "hour": "18:00",
        "day": "16/10/2025",
        "zone": "Europe/Madrid"
      },
      "details": {
        "competition": "Eurocup Women",
        "round": "Liga Regular"
      },
      "teams": {
        "local": {
          "name": "Start Lublin",
          "image": "https://static.futbolenlatv.com/img/20200730215740-mks-start-lublin.webp"
        },
        "visitor": {
          "name": "UZKK Student Niš",
          "image": "https://static.futbolenlatv.com/img/20250919100733-uzkk-student-nis.webp"
        }
      },
      "channels": [
        "FIBA YouTube"
      ],
      "event": {},
      "eventType": "match"
    },
    {
      "sport": "baloncesto",
      "date": {
        "hour": "18:00",
        "day": "16/10/2025",
        "zone": "Europe/Madrid"
      },
      "details": {
        "competition": "Eurocup Women",
        "round": "Liga Regular"
      },
      "teams": {
        "local": {
          "name": "Kibirkstis Vilnius",
          "image": "https://static.futbolenlatv.com/img/20241022175404-kibirkstis-vilnius.webp"
        },
        "visitor": {
          "name": "KB Peja",
          "image": "https://static.futbolenlatv.com/img/20250919083151-kb-peja.webp"
        }
      },
      "channels": [
        "FIBA YouTube"
      ],
      "event": {},
      "eventType": "match"
    },
    {
      "sport": "baloncesto",
      "date": {
        "hour": "18:00",
        "day": "16/10/2025",
        "zone": "Europe/Madrid"
      },
      "details": {
        "competition": "Eurocup Women",
        "round": "Liga Regular"
      },
      "teams": {
        "local": {
          "name": "Emlak Konut SK",
          "image": "https://static.futbolenlatv.com/img/20250919083133-emlak-konut-sk.webp"
        },
        "visitor": {
          "name": "TTT Riga",
          "image": "https://static.futbolenlatv.com/img/20201130101638-ttt-riga.webp"
        }
      },
      "channels": [
        "FIBA YouTube"
      ],
      "event": {},
      "eventType": "match"
    },
    {
      "sport": "baloncesto",
      "date": {
        "hour": "18:00",
        "day": "16/10/2025",
        "zone": "Europe/Madrid"
      },
      "details": {
        "competition": "Eurocup Women",
        "round": "Liga Regular"
      },
      "teams": {
        "local": {
          "name": "BC Beroe",
          "image": "https://static.futbolenlatv.com/img/20250919083258-bc-beroe.webp"
        },
        "visitor": {
          "name": "BCF Elfic Fribourg",
          "image": "https://static.futbolenlatv.com/img/20241018094816-bcf-elfic-fribourg.webp"
        }
      },
      "channels": [
        "FIBA YouTube"
      ],
      "event": {},
      "eventType": "match"
    },
    {
      "sport": "baloncesto",
      "date": {
        "hour": "18:00",
        "day": "16/10/2025",
        "zone": "Europe/Madrid"
      },
      "details": {
        "competition": "Euroliga",
        "round": "Liga Regular"
      },
      "teams": {
        "local": {
          "name": "Dubai Basketball",
          "image": "https://static.futbolenlatv.com/img/20250519204831-dubai-basketball.webp"
        },
        "visitor": {
          "name": "Barça Basket",
          "image": "https://static.futbolenlatv.com/img/20150808023001-barcelona-b.webp"
        }
      },
      "channels": [
        "M+ Vamos",
        "M+ #Vamos Bar",
        "Movistar+ Lite"
      ],
      "event": {},
      "eventType": "match"
    },
    {
      "sport": "baloncesto",
      "date": {
        "hour": "19:00",
        "day": "16/10/2025",
        "zone": "Europe/Madrid"
      },
      "details": {
        "competition": "Eurocup Women",
        "round": "Liga Regular"
      },
      "teams": {
        "local": {
          "name": "Besiktas JK Istanbul",
          "image": "https://static.futbolenlatv.com/img/20130815104433-besiktas.webp"
        },
        "visitor": {
          "name": "Athinaikos",
          "image": "https://static.futbolenlatv.com/img/20250919083234-athinaikos-basketball.webp"
        }
      },
      "channels": [
        "FIBA YouTube"
      ],
      "event": {},
      "eventType": "match"
    },
    {
      "sport": "baloncesto",
      "date": {
        "hour": "19:00",
        "day": "16/10/2025",
        "zone": "Europe/Madrid"
      },
      "details": {
        "competition": "Eurocup Women",
        "round": "Liga Regular"
      },
      "teams": {
        "local": {
          "name": "ŽKK Ragusa",
          "image": "https://static.futbolenlatv.com/img/20250919083217-zkk-ragusa.webp"
        },
        "visitor": {
          "name": "KP Brno",
          "image": "https://static.futbolenlatv.com/img/20240927155108-kp-brno.webp"
        }
      },
      "channels": [
        "FIBA YouTube"
      ],
      "event": {},
      "eventType": "match"
    },
    {
      "sport": "baloncesto",
      "date": {
        "hour": "19:00",
        "day": "16/10/2025",
        "zone": "Europe/Madrid"
      },
      "details": {
        "competition": "Euroliga",
        "round": "Liga Regular"
      },
      "teams": {
        "local": {
          "name": "Zalgiris Kaunas",
          "image": "https://static.futbolenlatv.com/img/20240318163809-zalgiris-kaunas.webp"
        },
        "visitor": {
          "name": "AX Olimpia Milano",
          "image": "https://static.futbolenlatv.com/img/20180129060055-ax-olimpia-milano.webp"
        }
      },
      "channels": [
        "M+ Deportes 4"
      ],
      "event": {},
      "eventType": "match"
    },
    {
      "sport": "baloncesto",
      "date": {
        "hour": "19:15",
        "day": "16/10/2025",
        "zone": "Europe/Madrid"
      },
      "details": {
        "competition": "Euroliga Femenina",
        "round": "Liga Regular"
      },
      "teams": {
        "local": {
          "name": "Valencia Basket",
          "image": "https://static.futbolenlatv.com/img/20130803090213-valencia-basket.webp"
        },
        "visitor": {
          "name": "Fenerbahce Istanbul",
          "image": "https://static.futbolenlatv.com/img/20130716022542-fenerbahce-ulker.webp"
        }
      },
      "channels": [
        "M+ Ellas Vamos : VER PARTIDO",
        "Movistar+ Lite",
        "À Punt Mèdia"
      ],
      "event": {},
      "eventType": "match"
    },
    {
      "sport": "baloncesto",
      "date": {
        "hour": "19:45",
        "day": "16/10/2025",
        "zone": "Europe/Madrid"
      },
      "details": {
        "competition": "Euroliga",
        "round": "Liga Regular"
      },
      "teams": {
        "local": {
          "name": "Fenerbahce Istanbul",
          "image": "https://static.futbolenlatv.com/img/20130716022542-fenerbahce-ulker.webp"
        },
        "visitor": {
          "name": "FC Bayern Basketball",
          "image": "https://static.futbolenlatv.com/img/20150901052257-fc-bayern-basketball.webp"
        }
      },
      "channels": [
        "M+ Deportes 2"
      ],
      "event": {},
      "eventType": "match"
    },
    {
      "sport": "baloncesto",
      "date": {
        "hour": "20:00",
        "day": "16/10/2025",
        "zone": "Europe/Madrid"
      },
      "details": {
        "competition": "Euroliga Femenina",
        "round": "Liga Regular"
      },
      "teams": {
        "local": {
          "name": "Casademont Zaragoza",
          "image": "https://static.futbolenlatv.com/img/20190925100947-casademont-zaragoza.webp"
        },
        "visitor": {
          "name": "Umana Reyer Venice",
          "image": "https://static.futbolenlatv.com/img/20151021114433-umana-reyer-venice.webp"
        }
      },
      "channels": [
        "Movistar Plus+ 2 : VER PARTIDO",
        "Aragón Deporte",
        "M+ Deportes 3",
        "Aragón TV"
      ],
      "event": {},
      "eventType": "match"
    },
    {
      "sport": "baloncesto",
      "date": {
        "hour": "20:00",
        "day": "16/10/2025",
        "zone": "Europe/Madrid"
      },
      "details": {
        "competition": "Eurocup Women",
        "round": "Liga Regular"
      },
      "teams": {
        "local": {
          "name": "Basket Montpellier",
          "image": "https://static.futbolenlatv.com/img/20190318094418-basket-montpellier.webp"
        },
        "visitor": {
          "name": "Dinamo Sassari",
          "image": "https://static.futbolenlatv.com/img/20131006071158-dinamo-sassari.webp"
        }
      },
      "channels": [
        "FIBA YouTube"
      ],
      "event": {},
      "eventType": "match"
    },
    {
      "sport": "baloncesto",
      "date": {
        "hour": "20:05",
        "day": "16/10/2025",
        "zone": "Europe/Madrid"
      },
      "details": {
        "competition": "Euroliga",
        "round": "Liga Regular"
      },
      "teams": {
        "local": {
          "name": "Maccabi Tel Aviv BC",
          "image": "https://static.futbolenlatv.com/img/20130716013716-maccabi-tel-aviv-bc.webp"
        },
        "visitor": {
          "name": "Olympiacos Piraeus",
          "image": "https://static.futbolenlatv.com/img/20130716014130-olympiacos-bc.webp"
        }
      },
      "channels": [
        "M+ Deportes"
      ],
      "event": {},
      "eventType": "match"
    },
    {
      "sport": "baloncesto",
      "date": {
        "hour": "22:30",
        "day": "16/10/2025",
        "zone": "Europe/Madrid"
      },
      "details": {
        "competition": "Eurocup Women",
        "round": "Liga Regular"
      },
      "teams": {
        "local": {
          "name": "Uniao Sportiva Azoris",
          "image": "https://static.futbolenlatv.com/img/20240927155058-uniao-sportiva.webp"
        },
        "visitor": {
          "name": "Elitzur Ramla",
          "image": "https://static.futbolenlatv.com/img/20241022175414-elitzur-ramla.webp"
        }
      },
      "channels": [
        "FIBA YouTube"
      ],
      "event": {},
      "eventType": "match"
    }
  ],
  "updated": "2025-10-16T00:12:52.722Z"
}