{
  "matches": [
    {
      "sport": "futbol",
      "date": {
        "hour": "00:00",
        "day": "20/03/2025",
        "zone": "Europe/Madrid"
      },
      "details": {
        "competition": "Campeonato Paranaense"
      },
      "teams": {
        "local": {
          "name": "At. Paranaense",
          "image": "https://static.futbolenlatv.com/img/32/20190513105130-atletico-paranaense.webp"
        },
        "visitor": {
          "name": "Maringá",
          "image": "https://static.futbolenlatv.com/img/32/20210517110636-maringa-fc.webp"
        }
      },
      "channels": [
        "Fanatiz"
      ],
      "event": {
        "name": "At. Paranaense - Maringá",
        "description": "At. Paranaense - Maringá el jueves, 20 de marzo de 2025 a las 0:00",
        "startDate": "2025-03-19T23:00:00",
        "duration": "T1H45M"
      }
    },
    {
      "sport": "futbol",
      "date": {
        "hour": "00:30",
        "day": "20/03/2025",
        "zone": "Europe/Madrid"
      },
      "details": {
        "competition": "Liga Colombiana",
        "round": "Torneo Apertura"
      },
      "teams": {
        "local": {
          "name": "Santa Fe",
          "image": "https://static.futbolenlatv.com/img/32/20140307121806-santa-fe.webp"
        },
        "visitor": {
          "name": "Bucaramanga",
          "image": "https://static.futbolenlatv.com/img/32/20140228090756-bucaramanga.webp"
        }
      },
      "channels": [
        "Fanatiz",
        "RCN Nuestra Tele"
      ],
      "event": {
        "name": "Santa Fe - Bucaramanga",
        "description": "Santa Fe - Bucaramanga el jueves, 20 de marzo de 2025 a las 0:30",
        "startDate": "2025-03-19T23:30:00",
        "duration": "T1H45M"
      }
    },
    {
      "sport": "futbol",
      "date": {
        "hour": "01:15",
        "day": "20/03/2025",
        "zone": "Europe/Madrid"
      },
      "details": {
        "competition": "Copa Argentina",
        "round": "1/32 de Final"
      },
      "teams": {
        "local": {
          "name": "River Plate",
          "image": "https://static.futbolenlatv.com/img/32/20121219051705_river-plate.webp"
        },
        "visitor": {
          "name": "Ciudad de Bolivar",
          "image": "https://static.futbolenlatv.com/img/32/20200306225848-club-ciudad-bolivar.webp"
        }
      },
      "channels": [
        "Fanatiz"
      ],
      "event": {
        "name": "River Plate - Ciudad de Bolivar",
        "description": "River Plate - Ciudad de Bolivar el jueves, 20 de marzo de 2025 a las 1:15",
        "startDate": "2025-03-20T00:15:00",
        "duration": "T1H45M"
      }
    },
    {
      "sport": "futbol",
      "date": {
        "hour": "02:30",
        "day": "20/03/2025",
        "zone": "Europe/Madrid"
      },
      "details": {
        "competition": "Liga Colombiana",
        "round": "Torneo Apertura"
      },
      "teams": {
        "local": {
          "name": "Atlético Nacional",
          "image": "https://static.futbolenlatv.com/img/32/20130528115548-Atletico-Nacional.webp"
        },
        "visitor": {
          "name": "Deportes Tolima",
          "image": "https://static.futbolenlatv.com/img/32/20201220191122-tolima.webp"
        }
      },
      "channels": [
        "Fanatiz",
        "RCN Nuestra Tele"
      ],
      "event": {
        "name": "Atlético Nacional - Deportes Tolima",
        "description": "Atlético Nacional - Deportes Tolima el jueves, 20 de marzo de 2025 a las 2:30",
        "startDate": "2025-03-20T01:30:00",
        "duration": "T1H45M"
      }
    },
    {
      "sport": "futbol",
      "date": {
        "hour": "10:10",
        "day": "20/03/2025",
        "zone": "Europe/Madrid"
      },
      "details": {
        "competition": "FIFA Copa Mundial 2026",
        "round": "Eliminatorias AFC"
      },
      "teams": {
        "local": {
          "name": "Australia",
          "image": "https://static.futbolenlatv.com/img/32/20130501101148_australia.webp"
        },
        "visitor": {
          "name": "Indonesia",
          "image": "https://static.futbolenlatv.com/img/32/20130606114453-indonesia.webp"
        }
      },
      "channels": [
        "OneFootball"
      ],
      "event": {
        "name": "Australia - Indonesia",
        "description": "Australia - Indonesia el jueves, 20 de marzo de 2025 a las 10:10",
        "startDate": "2025-03-20T09:10:00",
        "duration": "T1H45M"
      }
    },
    {
      "sport": "futbol",
      "date": {
        "hour": "11:35",
        "day": "20/03/2025",
        "zone": "Europe/Madrid"
      },
      "details": {
        "competition": "FIFA Copa Mundial 2026",
        "round": "Eliminatorias AFC"
      },
      "teams": {
        "local": {
          "name": "Japón",
          "image": "https://static.futbolenlatv.com/img/32/20130208071559_japon.webp"
        },
        "visitor": {
          "name": "Baréin",
          "image": "https://static.futbolenlatv.com/img/32/20131008054258-bahrein.webp"
        }
      },
      "channels": [
        "OneFootball"
      ],
      "event": {
        "name": "Japón - Baréin",
        "description": "Japón - Baréin el jueves, 20 de marzo de 2025 a las 11:35",
        "startDate": "2025-03-20T10:35:00",
        "duration": "T1H45M"
      }
    },
    {
      "sport": "futbol",
      "date": {
        "hour": "12:00",
        "day": "20/03/2025",
        "zone": "Europe/Madrid"
      },
      "details": {
        "competition": "FIFA Copa Mundial 2026",
        "round": "Eliminatorias AFC"
      },
      "teams": {
        "local": {
          "name": "Corea del Sur",
          "image": "https://static.futbolenlatv.com/img/32/20130507121229_coreadelsur.webp"
        },
        "visitor": {
          "name": "Omán",
          "image": "https://static.futbolenlatv.com/img/32/20130513104856_oman.webp"
        }
      },
      "channels": [
        "OneFootball"
      ],
      "event": {
        "name": "Corea del Sur - Omán",
        "description": "Corea del Sur - Omán el jueves, 20 de marzo de 2025 a las 12:00",
        "startDate": "2025-03-20T11:00:00",
        "duration": "T1H45M"
      }
    },
    {
      "sport": "futbol",
      "date": {
        "hour": "14:00",
        "day": "20/03/2025",
        "zone": "Europe/Madrid"
      },
      "details": {
        "competition": "FIFA Copa Mundial 2026",
        "round": "Eliminatorias CAF"
      },
      "teams": {
        "local": {
          "name": "Mozambique",
          "image": "https://static.futbolenlatv.com/img/32/20130712100714-mozambique.webp"
        },
        "visitor": {
          "name": "Uganda",
          "image": "https://static.futbolenlatv.com/img/32/20130712060740-uganda.webp"
        }
      },
      "channels": [
        "FIFA+"
      ],
      "event": {
        "name": "Mozambique - Uganda",
        "description": "Mozambique - Uganda el jueves, 20 de marzo de 2025 a las 14:00",
        "startDate": "2025-03-20T13:00:00",
        "duration": "T1H45M"
      }
    },
    {
      "sport": "futbol",
      "date": {
        "hour": "17:00",
        "day": "20/03/2025",
        "zone": "Europe/Madrid"
      },
      "details": {
        "competition": "FIFA Copa Mundial 2026",
        "round": "Eliminatorias CAF"
      },
      "teams": {
        "local": {
          "name": "Cabo Verde",
          "image": "https://static.futbolenlatv.com/img/32/20130103114415_cabo-verde.webp"
        },
        "visitor": {
          "name": "Mauricio",
          "image": "https://static.futbolenlatv.com/img/32/20130723025205-mauricio.webp"
        }
      },
      "channels": [
        "FIFA+"
      ],
      "event": {
        "name": "Cabo Verde - Mauricio",
        "description": "Cabo Verde - Mauricio el jueves, 20 de marzo de 2025 a las 17:00",
        "startDate": "2025-03-20T16:00:00",
        "duration": "T1H45M"
      }
    },
    {
      "sport": "futbol",
      "date": {
        "hour": "17:00",
        "day": "20/03/2025",
        "zone": "Europe/Madrid"
      },
      "details": {
        "competition": "FIFA Copa Mundial 2026",
        "round": "Eliminatorias AFC"
      },
      "teams": {
        "local": {
          "name": "Uzbekistán",
          "image": "https://static.futbolenlatv.com/img/32/20130507121244_uzbekistan.webp"
        },
        "visitor": {
          "name": "Kirguistán",
          "image": "https://static.futbolenlatv.com/img/32/20140519093750-kirguizistan.webp"
        }
      },
      "channels": [
        "OneFootball"
      ],
      "event": {
        "name": "Uzbekistán - Kirguistán",
        "description": "Uzbekistán - Kirguistán el jueves, 20 de marzo de 2025 a las 17:00",
        "startDate": "2025-03-20T16:00:00",
        "duration": "T1H45M"
      }
    },
    {
      "sport": "futbol",
      "date": {
        "hour": "17:00",
        "day": "20/03/2025",
        "zone": "Europe/Madrid"
      },
      "details": {
        "competition": "FIFA Copa Mundial 2026",
        "round": "Eliminatorias AFC"
      },
      "teams": {
        "local": {
          "name": "Irán",
          "image": "https://static.futbolenlatv.com/img/32/20130528074944-Iran.webp"
        },
        "visitor": {
          "name": "EAU",
          "image": "https://static.futbolenlatv.com/img/32/20130723025224-emirato-arabes-unido.webp"
        }
      },
      "channels": [
        "OneFootball"
      ],
      "event": {
        "name": "Irán - EAU",
        "description": "Irán - EAU el jueves, 20 de marzo de 2025 a las 17:00",
        "startDate": "2025-03-20T16:00:00",
        "duration": "T1H45M"
      }
    },
    {
      "sport": "futbol",
      "date": {
        "hour": "17:00",
        "day": "20/03/2025",
        "zone": "Europe/Madrid"
      },
      "details": {
        "competition": "FIFA Copa Mundial 2026",
        "round": "Eliminatorias CAF"
      },
      "teams": {
        "local": {
          "name": "Zimbabue",
          "image": "https://static.futbolenlatv.com/img/32/20130723025212-zimbaue.webp"
        },
        "visitor": {
          "name": "Benín",
          "image": "https://static.futbolenlatv.com/img/32/20141107103232-benin.webp"
        }
      },
      "channels": [
        "FIFA+"
      ],
      "event": {
        "name": "Zimbabue - Benín",
        "description": "Zimbabue - Benín el jueves, 20 de marzo de 2025 a las 17:00",
        "startDate": "2025-03-20T16:00:00",
        "duration": "T1H45M"
      }
    },
    {
      "sport": "futbol",
      "date": {
        "hour": "17:00",
        "day": "20/03/2025",
        "zone": "Europe/Madrid"
      },
      "details": {
        "competition": "FIFA Copa Mundial 2026",
        "round": "Eliminatorias CAF"
      },
      "teams": {
        "local": {
          "name": "Sierra Leona",
          "image": "https://static.futbolenlatv.com/img/32/20140830125555-sierra-leona.webp"
        },
        "visitor": {
          "name": "Guinea Bissau",
          "image": "https://static.futbolenlatv.com/img/32/20170103111543-guinea-bissau.webp"
        }
      },
      "channels": [
        "FIFA+"
      ],
      "event": {
        "name": "Sierra Leona - Guinea Bissau",
        "description": "Sierra Leona - Guinea Bissau el jueves, 20 de marzo de 2025 a las 17:00",
        "startDate": "2025-03-20T16:00:00",
        "duration": "T1H45M"
      }
    },
    {
      "sport": "futbol",
      "date": {
        "hour": "17:00",
        "day": "20/03/2025",
        "zone": "Europe/Madrid"
      },
      "details": {
        "competition": "FIFA Copa Mundial 2026",
        "round": "Eliminatorias CAF"
      },
      "teams": {
        "local": {
          "name": "Malaui",
          "image": "https://static.futbolenlatv.com/img/32/20141007074132-malaui.webp"
        },
        "visitor": {
          "name": "Namibia",
          "image": "https://static.futbolenlatv.com/img/32/20141210125124-namibia.webp"
        }
      },
      "channels": [
        "FIFA+"
      ],
      "event": {
        "name": "Malaui - Namibia",
        "description": "Malaui - Namibia el jueves, 20 de marzo de 2025 a las 17:00",
        "startDate": "2025-03-20T16:00:00",
        "duration": "T1H45M"
      }
    },
    {
      "sport": "futbol",
      "date": {
        "hour": "18:00",
        "day": "20/03/2025",
        "zone": "Europe/Madrid"
      },
      "details": {
        "competition": "UEFA Nations League",
        "round": "Playoff Ascenso/Descenso"
      },
      "teams": {
        "local": {
          "name": "Turquía",
          "image": "https://static.futbolenlatv.com/img/32/20130513110846_turquia.webp"
        },
        "visitor": {
          "name": "Hungría",
          "image": "https://static.futbolenlatv.com/img/32/20130530093548-Hungria.webp"
        }
      },
      "channels": [
        "UEFA TV PPV"
      ],
      "event": {
        "name": "Turquía - Hungría",
        "description": "Turquía - Hungría el jueves, 20 de marzo de 2025 a las 18:00",
        "startDate": "2025-03-20T17:00:00",
        "duration": "T1H45M"
      }
    },
    {
      "sport": "futbol",
      "date": {
        "hour": "18:00",
        "day": "20/03/2025",
        "zone": "Europe/Madrid"
      },
      "details": {
        "competition": "UEFA Nations League",
        "round": "Playoff Ascenso/Descenso"
      },
      "teams": {
        "local": {
          "name": "Armenia",
          "image": "https://static.futbolenlatv.com/img/32/20130604081815-Armenia.webp"
        },
        "visitor": {
          "name": "Georgia",
          "image": "https://static.futbolenlatv.com/img/32/20130318120408_georgia.webp"
        }
      },
      "channels": [
        "UEFA TV PPV"
      ],
      "event": {
        "name": "Armenia - Georgia",
        "description": "Armenia - Georgia el jueves, 20 de marzo de 2025 a las 18:00",
        "startDate": "2025-03-20T17:00:00",
        "duration": "T1H45M"
      }
    },
    {
      "sport": "futbol",
      "date": {
        "hour": "19:15",
        "day": "20/03/2025",
        "zone": "Europe/Madrid"
      },
      "details": {
        "competition": "FIFA Copa Mundial 2026",
        "round": "Eliminatorias AFC"
      },
      "teams": {
        "local": {
          "name": "Jordania",
          "image": "https://static.futbolenlatv.com/img/32/20130304045112_jordania.webp"
        },
        "visitor": {
          "name": "Palestina",
          "image": "https://static.futbolenlatv.com/img/32/20140519093504-palestina.webp"
        }
      },
      "channels": [
        "OneFootball"
      ],
      "event": {
        "name": "Jordania - Palestina",
        "description": "Jordania - Palestina el jueves, 20 de marzo de 2025 a las 19:15",
        "startDate": "2025-03-20T18:15:00",
        "duration": "T1H45M"
      }
    },
    {
      "sport": "futbol",
      "date": {
        "hour": "19:15",
        "day": "20/03/2025",
        "zone": "Europe/Madrid"
      },
      "details": {
        "competition": "FIFA Copa Mundial 2026",
        "round": "Eliminatorias AFC"
      },
      "teams": {
        "local": {
          "name": "Irak",
          "image": "https://static.futbolenlatv.com/img/32/20130513103718_irak.webp"
        },
        "visitor": {
          "name": "Kuwait",
          "image": "https://static.futbolenlatv.com/img/32/20130530093617-Kuwait.webp"
        }
      },
      "channels": [
        "OneFootball"
      ],
      "event": {
        "name": "Irak - Kuwait",
        "description": "Irak - Kuwait el jueves, 20 de marzo de 2025 a las 19:15",
        "startDate": "2025-03-20T18:15:00",
        "duration": "T1H45M"
      }
    },
    {
      "sport": "futbol",
      "date": {
        "hour": "19:15",
        "day": "20/03/2025",
        "zone": "Europe/Madrid"
      },
      "details": {
        "competition": "FIFA Copa Mundial 2026",
        "round": "Eliminatorias AFC"
      },
      "teams": {
        "local": {
          "name": "Catar",
          "image": "https://static.futbolenlatv.com/img/32/20130513104334_qatar.webp"
        },
        "visitor": {
          "name": "Corea del Norte",
          "image": "https://static.futbolenlatv.com/img/32/20131219074735-corea-del-norte.webp"
        }
      },
      "channels": [
        "OneFootball"
      ],
      "event": {
        "name": "Catar - Corea del Norte",
        "description": "Catar - Corea del Norte el jueves, 20 de marzo de 2025 a las 19:15",
        "startDate": "2025-03-20T18:15:00",
        "duration": "T1H45M"
      }
    },
    {
      "sport": "futbol",
      "date": {
        "hour": "19:15",
        "day": "20/03/2025",
        "zone": "Europe/Madrid"
      },
      "details": {
        "competition": "FIFA Copa Mundial 2026",
        "round": "Eliminatorias AFC"
      },
      "teams": {
        "local": {
          "name": "Arabia Saudí",
          "image": "https://static.futbolenlatv.com/img/32/20130730010609-arabia-saudi.webp"
        },
        "visitor": {
          "name": "China",
          "image": "https://static.futbolenlatv.com/img/32/20130221121827_china.webp"
        }
      },
      "channels": [
        "OneFootball"
      ],
      "event": {
        "name": "Arabia Saudí - China",
        "description": "Arabia Saudí - China el jueves, 20 de marzo de 2025 a las 19:15",
        "startDate": "2025-03-20T18:15:00",
        "duration": "T1H45M"
      }
    },
    {
      "sport": "futbol",
      "date": {
        "hour": "20:00",
        "day": "20/03/2025",
        "zone": "Europe/Madrid"
      },
      "details": {
        "competition": "FIFA Copa Mundial 2026",
        "round": "Eliminatorias CAF"
      },
      "teams": {
        "local": {
          "name": "Gabón",
          "image": "https://static.futbolenlatv.com/img/32/20130403093849_gabon.webp"
        },
        "visitor": {
          "name": "Seychelles",
          "image": "https://static.futbolenlatv.com/img/32/20150611073849-seychelles.webp"
        }
      },
      "channels": [
        "FIFA+"
      ],
      "event": {
        "name": "Gabón - Seychelles",
        "description": "Gabón - Seychelles el jueves, 20 de marzo de 2025 a las 20:00",
        "startDate": "2025-03-20T19:00:00",
        "duration": "T1H45M"
      }
    },
    {
      "sport": "futbol",
      "date": {
        "hour": "20:00",
        "day": "20/03/2025",
        "zone": "Europe/Madrid"
      },
      "details": {
        "competition": "FIFA Copa Mundial 2026",
        "round": "Eliminatorias CAF"
      },
      "teams": {
        "local": {
          "name": "Libia",
          "image": "https://static.futbolenlatv.com/img/32/20140110094203-libia.webp"
        },
        "visitor": {
          "name": "Angola",
          "image": "https://static.futbolenlatv.com/img/32/20130103113808_angola.webp"
        }
      },
      "channels": [
        "FIFA+"
      ],
      "event": {
        "name": "Libia - Angola",
        "description": "Libia - Angola el jueves, 20 de marzo de 2025 a las 20:00",
        "startDate": "2025-03-20T19:00:00",
        "duration": "T1H45M"
      }
    },
    {
      "sport": "futbol",
      "date": {
        "hour": "20:00",
        "day": "20/03/2025",
        "zone": "Europe/Madrid"
      },
      "details": {
        "competition": "FIFA Copa Mundial 2026",
        "round": "Eliminatorias CAF"
      },
      "teams": {
        "local": {
          "name": "Gambia",
          "image": "https://static.futbolenlatv.com/img/32/20190318113316-gambia.webp"
        },
        "visitor": {
          "name": "Kenia",
          "image": "https://static.futbolenlatv.com/img/32/20141007083536-kenia.webp"
        }
      },
      "channels": [
        "FIFA+"
      ],
      "event": {
        "name": "Gambia - Kenia",
        "description": "Gambia - Kenia el jueves, 20 de marzo de 2025 a las 20:00",
        "startDate": "2025-03-20T19:00:00",
        "duration": "T1H45M"
      }
    },
    {
      "sport": "futbol",
      "date": {
        "hour": "20:45",
        "day": "20/03/2025",
        "zone": "Europe/Madrid"
      },
      "details": {
        "competition": "UEFA Nations League",
        "round": "1/4 de Final"
      },
      "teams": {
        "local": {
          "name": "Italia",
          "image": "https://static.futbolenlatv.com/img/32/20130111045624_italia.webp"
        },
        "visitor": {
          "name": "Alemania",
          "image": "https://static.futbolenlatv.com/img/32/20130130075653_alemania.webp"
        }
      },
      "channels": [
        "UEFA TV PPV"
      ],
      "event": {
        "name": "Italia - Alemania",
        "description": "Italia - Alemania el jueves, 20 de marzo de 2025 a las 20:45",
        "startDate": "2025-03-20T19:45:00",
        "duration": "T1H45M"
      }
    },
    {
      "sport": "futbol",
      "date": {
        "hour": "20:45",
        "day": "20/03/2025",
        "zone": "Europe/Madrid"
      },
      "details": {
        "competition": "UEFA Nations League",
        "round": "1/4 de Final"
      },
      "teams": {
        "local": {
          "name": "Holanda",
          "image": "https://static.futbolenlatv.com/img/32/20130130075711_holanda.webp"
        },
        "visitor": {
          "name": "España",
          "image": "https://static.futbolenlatv.com/img/32/20130727123206-espana.webp"
        }
      },
      "channels": [
        "La 1 TVE",
        "RTVE Play"
      ],
      "event": {
        "name": "Holanda - España",
        "description": "Holanda - España el jueves, 20 de marzo de 2025 a las 20:45",
        "startDate": "2025-03-20T19:45:00",
        "duration": "T1H45M"
      }
    },
    {
      "sport": "futbol",
      "date": {
        "hour": "20:45",
        "day": "20/03/2025",
        "zone": "Europe/Madrid"
      },
      "details": {
        "competition": "UEFA Nations League",
        "round": "1/4 de Final"
      },
      "teams": {
        "local": {
          "name": "Dinamarca",
          "image": "https://static.futbolenlatv.com/img/32/20130207060752_dinamarca.webp"
        },
        "visitor": {
          "name": "Portugal",
          "image": "https://static.futbolenlatv.com/img/32/20130204101449_portugal.webp"
        }
      },
      "channels": [
        "UEFA TV PPV"
      ],
      "event": {
        "name": "Dinamarca - Portugal",
        "description": "Dinamarca - Portugal el jueves, 20 de marzo de 2025 a las 20:45",
        "startDate": "2025-03-20T19:45:00",
        "duration": "T1H45M"
      }
    },
    {
      "sport": "futbol",
      "date": {
        "hour": "20:45",
        "day": "20/03/2025",
        "zone": "Europe/Madrid"
      },
      "details": {
        "competition": "UEFA Nations League",
        "round": "Playoff Ascenso/Descenso"
      },
      "teams": {
        "local": {
          "name": "Ucrania",
          "image": "https://static.futbolenlatv.com/img/32/20130304045244_ucrania.webp"
        },
        "visitor": {
          "name": "Bélgica",
          "image": "https://static.futbolenlatv.com/img/32/20130121023530_belgica.webp"
        }
      },
      "channels": [
        "UEFA TV PPV"
      ],
      "event": {
        "name": "Ucrania - Bélgica",
        "description": "Ucrania - Bélgica el jueves, 20 de marzo de 2025 a las 20:45",
        "startDate": "2025-03-20T19:45:00",
        "duration": "T1H45M"
      }
    },
    {
      "sport": "futbol",
      "date": {
        "hour": "20:45",
        "day": "20/03/2025",
        "zone": "Europe/Madrid"
      },
      "details": {
        "competition": "UEFA Nations League",
        "round": "1/4 de Final"
      },
      "teams": {
        "local": {
          "name": "Croacia",
          "image": "https://static.futbolenlatv.com/img/32/20130317094139_croacia.webp"
        },
        "visitor": {
          "name": "Francia",
          "image": "https://static.futbolenlatv.com/img/32/20130124053558_francia.webp"
        }
      },
      "channels": [
        "UEFA TV PPV"
      ],
      "event": {
        "name": "Croacia - Francia",
        "description": "Croacia - Francia el jueves, 20 de marzo de 2025 a las 20:45",
        "startDate": "2025-03-20T19:45:00",
        "duration": "T1H45M"
      }
    },
    {
      "sport": "futbol",
      "date": {
        "hour": "20:45",
        "day": "20/03/2025",
        "zone": "Europe/Madrid"
      },
      "details": {
        "competition": "UEFA Nations League",
        "round": "Playoff Ascenso/Descenso"
      },
      "teams": {
        "local": {
          "name": "Grecia",
          "image": "https://static.futbolenlatv.com/img/32/20140624094707-grecia.webp"
        },
        "visitor": {
          "name": "Escocia",
          "image": "https://static.futbolenlatv.com/img/32/20130425075433_escocia.webp"
        }
      },
      "channels": [
        "UEFA TV PPV"
      ],
      "event": {
        "name": "Grecia - Escocia",
        "description": "Grecia - Escocia el jueves, 20 de marzo de 2025 a las 20:45",
        "startDate": "2025-03-20T19:45:00",
        "duration": "T1H45M"
      }
    },
    {
      "sport": "futbol",
      "date": {
        "hour": "20:45",
        "day": "20/03/2025",
        "zone": "Europe/Madrid"
      },
      "details": {
        "competition": "UEFA Nations League",
        "round": "Playoff Ascenso/Descenso"
      },
      "teams": {
        "local": {
          "name": "Austria",
          "image": "https://static.futbolenlatv.com/img/32/20130410124536_austria.webp"
        },
        "visitor": {
          "name": "Serbia",
          "image": "https://static.futbolenlatv.com/img/32/20130318120848_serbia.webp"
        }
      },
      "channels": [
        "UEFA TV PPV"
      ],
      "event": {
        "name": "Austria - Serbia",
        "description": "Austria - Serbia el jueves, 20 de marzo de 2025 a las 20:45",
        "startDate": "2025-03-20T19:45:00",
        "duration": "T1H45M"
      }
    },
    {
      "sport": "futbol",
      "date": {
        "hour": "20:45",
        "day": "20/03/2025",
        "zone": "Europe/Madrid"
      },
      "details": {
        "competition": "UEFA Nations League",
        "round": "Playoff Ascenso/Descenso"
      },
      "teams": {
        "local": {
          "name": "Eslovaquia",
          "image": "https://static.futbolenlatv.com/img/32/20130410124517_eslovaquia.webp"
        },
        "visitor": {
          "name": "Eslovenia",
          "image": "https://static.futbolenlatv.com/img/32/20130204101247_eslovenia.webp"
        }
      },
      "channels": [
        "UEFA TV PPV"
      ],
      "event": {
        "name": "Eslovaquia - Eslovenia",
        "description": "Eslovaquia - Eslovenia el jueves, 20 de marzo de 2025 a las 20:45",
        "startDate": "2025-03-20T19:45:00",
        "duration": "T1H45M"
      }
    },
    {
      "sport": "futbol",
      "date": {
        "hour": "20:45",
        "day": "20/03/2025",
        "zone": "Europe/Madrid"
      },
      "details": {
        "competition": "UEFA Nations League",
        "round": "Playoff Ascenso/Descenso"
      },
      "teams": {
        "local": {
          "name": "Bulgaria",
          "image": "https://static.futbolenlatv.com/img/32/20130528081800-Bulgaria.webp"
        },
        "visitor": {
          "name": "República Irlanda",
          "image": "https://static.futbolenlatv.com/img/32/20130521060225_republica-irlanda.webp"
        }
      },
      "channels": [
        "UEFA TV PPV"
      ],
      "event": {
        "name": "Bulgaria - República Irlanda",
        "description": "Bulgaria - República Irlanda el jueves, 20 de marzo de 2025 a las 20:45",
        "startDate": "2025-03-20T19:45:00",
        "duration": "T1H45M"
      }
    },
    {
      "sport": "futbol",
      "date": {
        "hour": "20:45",
        "day": "20/03/2025",
        "zone": "Europe/Madrid"
      },
      "details": {
        "competition": "UEFA Nations League",
        "round": "Playoff Ascenso/Descenso"
      },
      "teams": {
        "local": {
          "name": "Kosovo",
          "image": "https://static.futbolenlatv.com/img/32/20160819080945-kosovo.webp"
        },
        "visitor": {
          "name": "Islandia",
          "image": "https://static.futbolenlatv.com/img/32/20171107062145-islandia.webp"
        }
      },
      "channels": [
        "UEFA TV PPV"
      ],
      "event": {
        "name": "Kosovo - Islandia",
        "description": "Kosovo - Islandia el jueves, 20 de marzo de 2025 a las 20:45",
        "startDate": "2025-03-20T19:45:00",
        "duration": "T1H45M"
      }
    },
    {
      "sport": "futbol",
      "date": {
        "hour": "21:00",
        "day": "20/03/2025",
        "zone": "Europe/Madrid"
      },
      "details": {
        "competition": "Campeonato Uruguayo"
      },
      "teams": {
        "local": {
          "name": "Montevideo City Torque",
          "image": "https://static.futbolenlatv.com/img/32/20200807001922-ca-torque.webp"
        },
        "visitor": {
          "name": "CA Juventud",
          "image": "https://static.futbolenlatv.com/img/32/20141121093950-ca-juventud.webp"
        }
      },
      "channels": [
        "GolTV Play"
      ],
      "event": {
        "name": "Montevideo City Torque - CA Juventud",
        "description": "Montevideo City Torque - CA Juventud el jueves, 20 de marzo de 2025 a las 21:00",
        "startDate": "2025-03-20T20:00:00",
        "duration": "T1H45M"
      }
    },
    {
      "sport": "futbol",
      "date": {
        "hour": "22:00",
        "day": "20/03/2025",
        "zone": "Europe/Madrid"
      },
      "details": {
        "competition": "FIFA Copa Mundial 2026",
        "round": "Eliminatorias CAF"
      },
      "teams": {
        "local": {
          "name": "Comoras",
          "image": "https://static.futbolenlatv.com/img/32/20180903014739-comoras.webp"
        },
        "visitor": {
          "name": "Mali",
          "image": "https://static.futbolenlatv.com/img/32/20130103114840_mali.webp"
        }
      },
      "channels": [
        "FIFA+"
      ],
      "event": {
        "name": "Comoras - Mali",
        "description": "Comoras - Mali el jueves, 20 de marzo de 2025 a las 22:00",
        "startDate": "2025-03-20T21:00:00",
        "duration": "T1H45M"
      }
    }
  ],
  "updated": "2025-03-20T00:12:09.331Z"
}