{
  "matches": [
    {
      "sport": "futbol",
      "date": {
        "hour": "00:00",
        "day": "22/10/2025",
        "zone": "Europe/Madrid"
      },
      "details": {
        "competition": "Liga Primera Nicaragua",
        "round": null
      },
      "teams": {
        "local": {
          "name": "Real Madriz FC",
          "image": "https://static.futbolenlatv.com/img/20200802211622-real-madriz-fc.webp"
        },
        "visitor": {
          "name": "Club Sport Sébaco",
          "image": "https://static.futbolenlatv.com/img/20210627112125-hh-export-sebaco-fc.webp"
        }
      },
      "channels": [
        "FIFA+"
      ],
      "event": {
        "name": "Real Madriz FC - Club Sport Sébaco",
        "description": "Real Madriz FC - Club Sport Sébaco el miércoles, 22 de octubre de 2025 a las 0:00",
        "startDate": "2025-10-21T22:00:00",
        "duration": "T1H45M"
      },
      "eventType": "match"
    },
    {
      "sport": "futbol",
      "date": {
        "hour": "00:15",
        "day": "22/10/2025",
        "zone": "Europe/Madrid"
      },
      "details": {
        "competition": "Primera División Argentina",
        "round": "Torneo Clausura"
      },
      "teams": {
        "local": {
          "name": "Unión Santa Fe",
          "image": "https://static.futbolenlatv.com/img/20160115093449-union-santa-fe.webp"
        },
        "visitor": {
          "name": "Defensa y Justicia",
          "image": "https://static.futbolenlatv.com/img/20140621094213-defensa-y-justicia.webp"
        }
      },
      "channels": [
        "Fanatiz"
      ],
      "event": {
        "name": "Unión Santa Fe - Defensa y Justicia",
        "description": "Unión Santa Fe - Defensa y Justicia el miércoles, 22 de octubre de 2025 a las 0:15",
        "startDate": "2025-10-21T22:15:00",
        "duration": "T1H45M"
      },
      "eventType": "match"
    },
    {
      "sport": "futbol",
      "date": {
        "hour": "01:00",
        "day": "22/10/2025",
        "zone": "Europe/Madrid"
      },
      "details": {
        "competition": "Liga Colombiana",
        "round": null
      },
      "teams": {
        "local": {
          "name": "Millonarios",
          "image": "https://static.futbolenlatv.com/img/20130210120225_millonarios.webp"
        },
        "visitor": {
          "name": "Bucaramanga",
          "image": "https://static.futbolenlatv.com/img/20140228090756-bucaramanga.webp"
        }
      },
      "channels": [
        "RCN Nuestra Tele"
      ],
      "event": {
        "name": "Millonarios - Bucaramanga",
        "description": "Millonarios - Bucaramanga el miércoles, 22 de octubre de 2025 a las 1:00",
        "startDate": "2025-10-21T23:00:00",
        "duration": "T1H45M"
      },
      "eventType": "match"
    },
    {
      "sport": "futbol",
      "date": {
        "hour": "02:30",
        "day": "22/10/2025",
        "zone": "Europe/Madrid"
      },
      "details": {
        "competition": "Copa Sudamericana",
        "round": "Semifinales"
      },
      "teams": {
        "local": {
          "name": "Independiente del Valle",
          "image": "https://static.futbolenlatv.com/img/20191111111808-independiente-del-valle.webp"
        },
        "visitor": {
          "name": "Atlético Mineiro",
          "image": "https://static.futbolenlatv.com/img/20180202125146-atletico-mineiro.webp"
        }
      },
      "channels": [
        "M+ Vamos",
        "M+ #Vamos Bar",
        "Movistar+ Lite",
        "LaLiga+ Plus",
        "M+ Liga de Campeones"
      ],
      "event": {
        "name": "Independiente del Valle - Atlético Mineiro",
        "description": "Independiente del Valle - Atlético Mineiro el miércoles, 22 de octubre de 2025 a las 2:30",
        "startDate": "2025-10-22T00:30:00",
        "duration": "T1H45M"
      },
      "eventType": "match"
    },
    {
      "sport": "futbol",
      "date": {
        "hour": "12:00",
        "day": "22/10/2025",
        "zone": "Europe/Madrid"
      },
      "details": {
        "competition": "AFC Champions League Elite",
        "round": null
      },
      "teams": {
        "local": {
          "name": "Gangwon FC",
          "image": "https://static.futbolenlatv.com/img/20200507195447-gangwon-fc.webp"
        },
        "visitor": {
          "name": "Vissel Kobe",
          "image": "https://static.futbolenlatv.com/img/20141102091154-vissel-kobe.webp"
        }
      },
      "channels": [
        "The AFC Hub YouTube",
        "OneFootball PPV",
        "OneFootball"
      ],
      "event": {
        "name": "Gangwon FC - Vissel Kobe",
        "description": "Gangwon FC - Vissel Kobe el miércoles, 22 de octubre de 2025 a las 12:00",
        "startDate": "2025-10-22T10:00:00",
        "duration": "T1H45M"
      },
      "eventType": "match"
    },
    {
      "sport": "futbol",
      "date": {
        "hour": "12:00",
        "day": "22/10/2025",
        "zone": "Europe/Madrid"
      },
      "details": {
        "competition": "AFC Champions League Two",
        "round": null
      },
      "teams": {
        "local": {
          "name": "Gamba Osaka",
          "image": "https://static.futbolenlatv.com/img/20220906193508-gamba-osaka.webp"
        },
        "visitor": {
          "name": "Nam Định FC",
          "image": "https://static.futbolenlatv.com/img/20240914100607-nam-dinh-fc.webp"
        }
      },
      "channels": [
        "The AFC Hub YouTube",
        "OneFootball"
      ],
      "event": {
        "name": "Gamba Osaka - Nam Định FC",
        "description": "Gamba Osaka - Nam Định FC el miércoles, 22 de octubre de 2025 a las 12:00",
        "startDate": "2025-10-22T10:00:00",
        "duration": "T1H45M"
      },
      "eventType": "match"
    },
    {
      "sport": "futbol",
      "date": {
        "hour": "12:00",
        "day": "22/10/2025",
        "zone": "Europe/Madrid"
      },
      "details": {
        "competition": "UEFA Youth League",
        "round": "Fase Liga"
      },
      "teams": {
        "local": {
          "name": "Athletic Club Academy",
          "image": "https://static.futbolenlatv.com/img/20151130110649-athletic.webp"
        },
        "visitor": {
          "name": "Qarabag FK Academy",
          "image": "https://static.futbolenlatv.com/img/20130813080725-qarabag-fk.webp"
        }
      },
      "channels": [
        "Canal por confirmar"
      ],
      "event": {
        "name": "Athletic Club Academy - Qarabag FK Academy",
        "description": "Athletic Club Academy - Qarabag FK Academy el miércoles, 22 de octubre de 2025 a las 12:00",
        "startDate": "2025-10-22T10:00:00",
        "duration": "T1H45M"
      },
      "eventType": "match"
    },
    {
      "sport": "futbol",
      "date": {
        "hour": "14:00",
        "day": "22/10/2025",
        "zone": "Europe/Madrid"
      },
      "details": {
        "competition": "UEFA Youth League",
        "round": "Fase Liga"
      },
      "teams": {
        "local": {
          "name": "AS Monaco Academy",
          "image": "https://static.futbolenlatv.com/img/20240923180801-as-monaco-academy.webp"
        },
        "visitor": {
          "name": "Tottenham Academy",
          "image": "https://static.futbolenlatv.com/img/20200413194314-tottenham-academy.webp"
        }
      },
      "channels": [
        "UEFA TV",
        "M+ Liga de Campeones 2"
      ],
      "event": {
        "name": "AS Monaco Academy - Tottenham Academy",
        "description": "AS Monaco Academy - Tottenham Academy el miércoles, 22 de octubre de 2025 a las 14:00",
        "startDate": "2025-10-22T12:00:00",
        "duration": "T1H45M"
      },
      "eventType": "match"
    },
    {
      "sport": "futbol",
      "date": {
        "hour": "14:15",
        "day": "22/10/2025",
        "zone": "Europe/Madrid"
      },
      "details": {
        "competition": "AFC Champions League Elite",
        "round": null
      },
      "teams": {
        "local": {
          "name": "Shanghai Shenhua",
          "image": "https://static.futbolenlatv.com/img/20160205112207-shanghai-shenhua.webp"
        },
        "visitor": {
          "name": "Seoul",
          "image": "https://static.futbolenlatv.com/img/20130507063602_seoul.webp"
        }
      },
      "channels": [
        "The AFC Hub YouTube",
        "OneFootball PPV",
        "OneFootball"
      ],
      "event": {
        "name": "Shanghai Shenhua - Seoul",
        "description": "Shanghai Shenhua - Seoul el miércoles, 22 de octubre de 2025 a las 14:15",
        "startDate": "2025-10-22T12:15:00",
        "duration": "T1H45M"
      },
      "eventType": "match"
    },
    {
      "sport": "futbol",
      "date": {
        "hour": "14:15",
        "day": "22/10/2025",
        "zone": "Europe/Madrid"
      },
      "details": {
        "competition": "AFC Champions League Two",
        "round": null
      },
      "teams": {
        "local": {
          "name": "Ratchaburi FC",
          "image": "https://static.futbolenlatv.com/img/20210617115623-ratchaburi-mitr-phol-fc.webp"
        },
        "visitor": {
          "name": "Eastern Long Lions",
          "image": "https://static.futbolenlatv.com/img/20210616172744-eastern-sc.webp"
        }
      },
      "channels": [
        "The AFC Hub YouTube",
        "OneFootball"
      ],
      "event": {
        "name": "Ratchaburi FC - Eastern Long Lions",
        "description": "Ratchaburi FC - Eastern Long Lions el miércoles, 22 de octubre de 2025 a las 14:15",
        "startDate": "2025-10-22T12:15:00",
        "duration": "T1H45M"
      },
      "eventType": "match"
    },
    {
      "sport": "futbol",
      "date": {
        "hour": "15:00",
        "day": "22/10/2025",
        "zone": "Europe/Madrid"
      },
      "details": {
        "competition": "FIFA Mundial Femenino Sub-17",
        "round": "Fase de grupos"
      },
      "teams": {
        "local": {
          "name": "España",
          "image": "https://static.futbolenlatv.com/img/20130727123206-espana.webp"
        },
        "visitor": {
          "name": "Corea del Sur",
          "image": "https://static.futbolenlatv.com/img/20130507121229_coreadelsur.webp"
        }
      },
      "channels": [
        "FIFA+",
        "Teledeporte",
        "RTVE Play"
      ],
      "event": {
        "name": "España - Corea del Sur",
        "description": "España - Corea del Sur el miércoles, 22 de octubre de 2025 a las 15:00",
        "startDate": "2025-10-22T13:00:00",
        "duration": "T1H45M"
      },
      "eventType": "match"
    },
    {
      "sport": "futbol",
      "date": {
        "hour": "15:00",
        "day": "22/10/2025",
        "zone": "Europe/Madrid"
      },
      "details": {
        "competition": "UEFA Youth League",
        "round": "Fase Liga"
      },
      "teams": {
        "local": {
          "name": "Sporting CP Academy",
          "image": "https://static.futbolenlatv.com/img/20150920013529-sporting-portugal.webp"
        },
        "visitor": {
          "name": "O. Marseille Academy",
          "image": "https://static.futbolenlatv.com/img/20130117033826_olympique-de-marseille.webp"
        }
      },
      "channels": [
        "M+ Liga de Campeones 3"
      ],
      "event": {
        "name": "Sporting CP Academy - O. Marseille Academy",
        "description": "Sporting CP Academy - O. Marseille Academy el miércoles, 22 de octubre de 2025 a las 15:00",
        "startDate": "2025-10-22T13:00:00",
        "duration": "T1H45M"
      },
      "eventType": "match"
    },
    {
      "sport": "futbol",
      "date": {
        "hour": "15:45",
        "day": "22/10/2025",
        "zone": "Europe/Madrid"
      },
      "details": {
        "competition": "AFC Champions League Two",
        "round": null
      },
      "teams": {
        "local": {
          "name": "FC Goa",
          "image": "https://static.futbolenlatv.com/img/20141014051907-fc-goa.webp"
        },
        "visitor": {
          "name": "Al Nassr",
          "image": "https://static.futbolenlatv.com/img/20240522170910-al-nassr.webp"
        }
      },
      "channels": [
        "The AFC Hub YouTube",
        "OneFootball"
      ],
      "event": {
        "name": "FC Goa - Al Nassr",
        "description": "FC Goa - Al Nassr el miércoles, 22 de octubre de 2025 a las 15:45",
        "startDate": "2025-10-22T13:45:00",
        "duration": "T1H45M"
      },
      "eventType": "match"
    },
    {
      "sport": "futbol",
      "date": {
        "hour": "15:45",
        "day": "22/10/2025",
        "zone": "Europe/Madrid"
      },
      "details": {
        "competition": "AFC Champions League Two",
        "round": null
      },
      "teams": {
        "local": {
          "name": "Istiklol",
          "image": "https://static.futbolenlatv.com/img/20150220120619-istiklol.webp"
        },
        "visitor": {
          "name": "Al-Zawraa SC",
          "image": "https://static.futbolenlatv.com/img/20220328174011-al-zawraa-sc.webp"
        }
      },
      "channels": [
        "The AFC Hub YouTube",
        "OneFootball"
      ],
      "event": {
        "name": "Istiklol - Al-Zawraa SC",
        "description": "Istiklol - Al-Zawraa SC el miércoles, 22 de octubre de 2025 a las 15:45",
        "startDate": "2025-10-22T13:45:00",
        "duration": "T1H45M"
      },
      "eventType": "match"
    },
    {
      "sport": "futbol",
      "date": {
        "hour": "15:45",
        "day": "22/10/2025",
        "zone": "Europe/Madrid"
      },
      "details": {
        "competition": "AFC Champions League Two",
        "round": null
      },
      "teams": {
        "local": {
          "name": "FC Andijon",
          "image": "https://static.futbolenlatv.com/img/20250912083536-fc-andijon.webp"
        },
        "visitor": {
          "name": "Al Khalidiya FC",
          "image": "https://static.futbolenlatv.com/img/20220114091447-al-khalidiya-fc.webp"
        }
      },
      "channels": [
        "The AFC Hub YouTube",
        "OneFootball"
      ],
      "event": {
        "name": "FC Andijon - Al Khalidiya FC",
        "description": "FC Andijon - Al Khalidiya FC el miércoles, 22 de octubre de 2025 a las 15:45",
        "startDate": "2025-10-22T13:45:00",
        "duration": "T1H45M"
      },
      "eventType": "match"
    },
    {
      "sport": "futbol",
      "date": {
        "hour": "16:00",
        "day": "22/10/2025",
        "zone": "Europe/Madrid"
      },
      "details": {
        "competition": "UEFA Youth League",
        "round": "Fase Liga"
      },
      "teams": {
        "local": {
          "name": "Real Madrid Academy",
          "image": "https://static.futbolenlatv.com/img/20160725122745-real-madrid.webp"
        },
        "visitor": {
          "name": "Juventus Academy",
          "image": "https://static.futbolenlatv.com/img/20170117094900-juventus.webp"
        }
      },
      "channels": [
        "M+ Liga de Campeones",
        "Real Madrid TV"
      ],
      "event": {
        "name": "Real Madrid Academy - Juventus Academy",
        "description": "Real Madrid Academy - Juventus Academy el miércoles, 22 de octubre de 2025 a las 16:00",
        "startDate": "2025-10-22T14:00:00",
        "duration": "T1H45M"
      },
      "eventType": "match"
    },
    {
      "sport": "futbol",
      "date": {
        "hour": "16:00",
        "day": "22/10/2025",
        "zone": "Europe/Madrid"
      },
      "details": {
        "competition": "UEFA Youth League",
        "round": "Fase Liga"
      },
      "teams": {
        "local": {
          "name": "Bayern Academy",
          "image": "https://static.futbolenlatv.com/img/20140731073126-bayern-munich.webp"
        },
        "visitor": {
          "name": "Club Brugge Academy",
          "image": "https://static.futbolenlatv.com/img/20190922105951-Club-Brugge.webp"
        }
      },
      "channels": [
        "UEFA TV",
        "M+ Liga de Campeones 2"
      ],
      "event": {
        "name": "Bayern Academy - Club Brugge Academy",
        "description": "Bayern Academy - Club Brugge Academy el miércoles, 22 de octubre de 2025 a las 16:00",
        "startDate": "2025-10-22T14:00:00",
        "duration": "T1H45M"
      },
      "eventType": "match"
    },
    {
      "sport": "futbol",
      "date": {
        "hour": "17:00",
        "day": "22/10/2025",
        "zone": "Europe/Madrid"
      },
      "details": {
        "competition": "Veikkausliiga",
        "round": null
      },
      "teams": {
        "local": {
          "name": "FC Inter Turku",
          "image": "https://static.futbolenlatv.com/img/20220323211929-fc-inter-turku.webp"
        },
        "visitor": {
          "name": "Gnistan",
          "image": "https://static.futbolenlatv.com/img/20220408180524-gnistan.webp"
        }
      },
      "channels": [
        "OneFootball"
      ],
      "event": {
        "name": "FC Inter Turku - Gnistan",
        "description": "FC Inter Turku - Gnistan el miércoles, 22 de octubre de 2025 a las 17:00",
        "startDate": "2025-10-22T15:00:00",
        "duration": "T1H45M"
      },
      "eventType": "match"
    },
    {
      "sport": "futbol",
      "date": {
        "hour": "18:00",
        "day": "22/10/2025",
        "zone": "Europe/Madrid"
      },
      "details": {
        "competition": "AFC Champions League Two",
        "round": null
      },
      "teams": {
        "local": {
          "name": "Esteghlal",
          "image": "https://static.futbolenlatv.com/img/20130416064510_esteghlal.webp"
        },
        "visitor": {
          "name": "Al Wehdat",
          "image": "https://static.futbolenlatv.com/img/20150206102616-al-wehdat.webp"
        }
      },
      "channels": [
        "The AFC Hub YouTube",
        "OneFootball"
      ],
      "event": {
        "name": "Esteghlal - Al Wehdat",
        "description": "Esteghlal - Al Wehdat el miércoles, 22 de octubre de 2025 a las 18:00",
        "startDate": "2025-10-22T16:00:00",
        "duration": "T1H45M"
      },
      "eventType": "match"
    },
    {
      "sport": "futbol",
      "date": {
        "hour": "18:00",
        "day": "22/10/2025",
        "zone": "Europe/Madrid"
      },
      "details": {
        "competition": "AFC Champions League Two",
        "round": null
      },
      "teams": {
        "local": {
          "name": "Al Ahli SC",
          "image": "https://static.futbolenlatv.com/img/20130501111059_al-ahli-sc.webp"
        },
        "visitor": {
          "name": "FK Arkadag",
          "image": "https://static.futbolenlatv.com/img/20241101102834-fk-arkadag.webp"
        }
      },
      "channels": [
        "The AFC Hub YouTube",
        "OneFootball"
      ],
      "event": {
        "name": "Al Ahli SC - FK Arkadag",
        "description": "Al Ahli SC - FK Arkadag el miércoles, 22 de octubre de 2025 a las 18:00",
        "startDate": "2025-10-22T16:00:00",
        "duration": "T1H45M"
      },
      "eventType": "match"
    },
    {
      "sport": "futbol",
      "date": {
        "hour": "18:00",
        "day": "22/10/2025",
        "zone": "Europe/Madrid"
      },
      "details": {
        "competition": "FIFA Mundial Femenino Sub-17",
        "round": "Fase de grupos"
      },
      "teams": {
        "local": {
          "name": "Japón",
          "image": "https://static.futbolenlatv.com/img/20130208071559_japon.webp"
        },
        "visitor": {
          "name": "Zambia",
          "image": "https://static.futbolenlatv.com/img/20130103115245_zambia.webp"
        }
      },
      "channels": [
        "FIFA+"
      ],
      "event": {
        "name": "Japón - Zambia",
        "description": "Japón - Zambia el miércoles, 22 de octubre de 2025 a las 18:00",
        "startDate": "2025-10-22T16:00:00",
        "duration": "T1H45M"
      },
      "eventType": "match"
    },
    {
      "sport": "futbol",
      "date": {
        "hour": "18:00",
        "day": "22/10/2025",
        "zone": "Europe/Madrid"
      },
      "details": {
        "competition": "FIFA Mundial Femenino Sub-17",
        "round": "Fase de grupos"
      },
      "teams": {
        "local": {
          "name": "Samoa",
          "image": "https://static.futbolenlatv.com/img/20141210125136-samoa.webp"
        },
        "visitor": {
          "name": "Canadá",
          "image": "https://static.futbolenlatv.com/img/20130625051127-Canada.webp"
        }
      },
      "channels": [
        "FIFA+"
      ],
      "event": {
        "name": "Samoa - Canadá",
        "description": "Samoa - Canadá el miércoles, 22 de octubre de 2025 a las 18:00",
        "startDate": "2025-10-22T16:00:00",
        "duration": "T1H45M"
      },
      "eventType": "match"
    },
    {
      "sport": "futbol",
      "date": {
        "hour": "18:00",
        "day": "22/10/2025",
        "zone": "Europe/Madrid"
      },
      "details": {
        "competition": "Veikkausliiga",
        "round": null
      },
      "teams": {
        "local": {
          "name": "HJK Helsinki",
          "image": "https://static.futbolenlatv.com/img/20140606110141-hjk-helsinki.webp"
        },
        "visitor": {
          "name": "SJK Seinäjoki",
          "image": "https://static.futbolenlatv.com/img/20220323212013-sjk-seinajoki.webp"
        }
      },
      "channels": [
        "OneFootball"
      ],
      "event": {
        "name": "HJK Helsinki - SJK Seinäjoki",
        "description": "HJK Helsinki - SJK Seinäjoki el miércoles, 22 de octubre de 2025 a las 18:00",
        "startDate": "2025-10-22T16:00:00",
        "duration": "T1H45M"
      },
      "eventType": "match"
    },
    {
      "sport": "futbol",
      "date": {
        "hour": "18:45",
        "day": "22/10/2025",
        "zone": "Europe/Madrid"
      },
      "details": {
        "competition": "Champions League",
        "round": "Fase Liga"
      },
      "teams": {
        "local": {
          "name": "Athletic Club",
          "image": "https://static.futbolenlatv.com/img/20121218093611_bilbao.webp"
        },
        "visitor": {
          "name": "Qarabag FK",
          "image": "https://static.futbolenlatv.com/img/20130813080725-qarabag-fk.webp"
        }
      },
      "channels": [
        "M+ Liga de Campeones",
        "LaLiga TV Bar"
      ],
      "event": {
        "name": "Athletic Club - Qarabag FK",
        "description": "Athletic Club - Qarabag FK el miércoles, 22 de octubre de 2025 a las 18:45",
        "startDate": "2025-10-22T16:45:00",
        "duration": "T1H45M"
      },
      "eventType": "match"
    },
    {
      "sport": "futbol",
      "date": {
        "hour": "18:45",
        "day": "22/10/2025",
        "zone": "Europe/Madrid"
      },
      "details": {
        "competition": "Champions League",
        "round": "Fase Liga"
      },
      "teams": {
        "local": {
          "name": "Galatasaray",
          "image": "https://static.futbolenlatv.com/img/20151015094401-galatasaray.webp"
        },
        "visitor": {
          "name": "Bodø/Glimt",
          "image": "https://static.futbolenlatv.com/img/20200603232642-bodo-glimt.webp"
        }
      },
      "channels": [
        "M+ Liga de Campeones 3"
      ],
      "event": {
        "name": "Galatasaray - Bodø/Glimt",
        "description": "Galatasaray - Bodø/Glimt el miércoles, 22 de octubre de 2025 a las 18:45",
        "startDate": "2025-10-22T16:45:00",
        "duration": "T1H45M"
      },
      "eventType": "match"
    },
    {
      "sport": "futbol",
      "date": {
        "hour": "19:00",
        "day": "22/10/2025",
        "zone": "Europe/Madrid"
      },
      "details": {
        "competition": "UEFA Youth League",
        "round": "Ruta de Campeones Nacionales"
      },
      "teams": {
        "local": {
          "name": "FC Basel Academy",
          "image": "https://static.futbolenlatv.com/img/20121221103501_basel.webp"
        },
        "visitor": {
          "name": "Real Betis Academy",
          "image": "https://static.futbolenlatv.com/img/20160830072242-real-betis.webp"
        }
      },
      "channels": [
        "Canal por confirmar"
      ],
      "event": {
        "name": "FC Basel Academy - Real Betis Academy",
        "description": "FC Basel Academy - Real Betis Academy el miércoles, 22 de octubre de 2025 a las 19:00",
        "startDate": "2025-10-22T17:00:00",
        "duration": "T1H45M"
      },
      "eventType": "match"
    },
    {
      "sport": "futbol",
      "date": {
        "hour": "19:00",
        "day": "22/10/2025",
        "zone": "Europe/Madrid"
      },
      "details": {
        "competition": "Primera Federación",
        "round": "Grupo 2"
      },
      "teams": {
        "local": {
          "name": "Hércules",
          "image": "https://static.futbolenlatv.com/img/20121218094521_hercules.webp"
        },
        "visitor": {
          "name": "Atlético Madrileño",
          "image": "https://static.futbolenlatv.com/img/20240712123955-at-madrid-b.webp"
        }
      },
      "channels": [
        "LaLiga+ Plus",
        "TV FootballClub",
        "Primera Federación"
      ],
      "event": {
        "name": "Hércules - Atlético Madrileño",
        "description": "Hércules - Atlético Madrileño el miércoles, 22 de octubre de 2025 a las 19:00",
        "startDate": "2025-10-22T17:00:00",
        "duration": "T1H45M"
      },
      "eventType": "match"
    },
    {
      "sport": "futbol",
      "date": {
        "hour": "20:15",
        "day": "22/10/2025",
        "zone": "Europe/Madrid"
      },
      "details": {
        "competition": "AFC Champions League Two",
        "round": null
      },
      "teams": {
        "local": {
          "name": "Al Muharraq",
          "image": "https://static.futbolenlatv.com/img/20130422093956_al-muharraq.webp"
        },
        "visitor": {
          "name": "Al Wasl",
          "image": "https://static.futbolenlatv.com/img/20180723114716-al-wasl.webp"
        }
      },
      "channels": [
        "The AFC Hub YouTube",
        "OneFootball"
      ],
      "event": {
        "name": "Al Muharraq - Al Wasl",
        "description": "Al Muharraq - Al Wasl el miércoles, 22 de octubre de 2025 a las 20:15",
        "startDate": "2025-10-22T18:15:00",
        "duration": "T1H45M"
      },
      "eventType": "match"
    },
    {
      "sport": "futbol",
      "date": {
        "hour": "21:00",
        "day": "22/10/2025",
        "zone": "Europe/Madrid"
      },
      "details": {
        "competition": "Champions League",
        "round": "Fase Liga"
      },
      "teams": {
        "local": {
          "name": "Real Madrid",
          "image": "https://static.futbolenlatv.com/img/20160725122745-real-madrid.webp"
        },
        "visitor": {
          "name": "Juventus",
          "image": "https://static.futbolenlatv.com/img/20170117094900-juventus.webp"
        }
      },
      "channels": [
        "Movistar Plus+ : VER PARTIDO",
        "Orange Fútbol 1",
        "M+ Liga de Campeones",
        "M+ Liga de Campeones 4",
        "LaLiga TV Bar"
      ],
      "event": {
        "name": "Real Madrid - Juventus",
        "description": "Real Madrid - Juventus el miércoles, 22 de octubre de 2025 a las 21:00",
        "startDate": "2025-10-22T19:00:00",
        "duration": "T1H45M"
      },
      "eventType": "match"
    },
    {
      "sport": "futbol",
      "date": {
        "hour": "21:00",
        "day": "22/10/2025",
        "zone": "Europe/Madrid"
      },
      "details": {
        "competition": "Champions League",
        "round": "Fase Liga"
      },
      "teams": {
        "local": {
          "name": "Chelsea",
          "image": "https://static.futbolenlatv.com/img/20121218101333_chelsea.webp"
        },
        "visitor": {
          "name": "Ajax",
          "image": "https://static.futbolenlatv.com/img/20121219035603_ajax.webp"
        }
      },
      "channels": [
        "M+ Liga de Campeones 3",
        "M+ Liga de Campeones 4"
      ],
      "event": {
        "name": "Chelsea - Ajax",
        "description": "Chelsea - Ajax el miércoles, 22 de octubre de 2025 a las 21:00",
        "startDate": "2025-10-22T19:00:00",
        "duration": "T1H45M"
      },
      "eventType": "match"
    },
    {
      "sport": "futbol",
      "date": {
        "hour": "21:00",
        "day": "22/10/2025",
        "zone": "Europe/Madrid"
      },
      "details": {
        "competition": "Champions League",
        "round": "Fase Liga"
      },
      "teams": {
        "local": {
          "name": "FC Bayern",
          "image": "https://static.futbolenlatv.com/img/20121218101641_bayern-munich.webp"
        },
        "visitor": {
          "name": "Club Brugge",
          "image": "https://static.futbolenlatv.com/img/20121222102302_club-brugge.webp"
        }
      },
      "channels": [
        "M+ Liga de Campeones 4",
        "M+ Liga de Campeones 6"
      ],
      "event": {
        "name": "FC Bayern - Club Brugge",
        "description": "FC Bayern - Club Brugge el miércoles, 22 de octubre de 2025 a las 21:00",
        "startDate": "2025-10-22T19:00:00",
        "duration": "T1H45M"
      },
      "eventType": "match"
    },
    {
      "sport": "futbol",
      "date": {
        "hour": "21:00",
        "day": "22/10/2025",
        "zone": "Europe/Madrid"
      },
      "details": {
        "competition": "Champions League",
        "round": "Fase Liga"
      },
      "teams": {
        "local": {
          "name": "Eintracht Frankfurt",
          "image": "https://static.futbolenlatv.com/img/20121218101809_eintracht-frankfurt.webp"
        },
        "visitor": {
          "name": "Liverpool",
          "image": "https://static.futbolenlatv.com/img/20240923180620-liverpool.webp"
        }
      },
      "channels": [
        "M+ Liga de Campeones 4",
        "M+ Liga de Campeones 5"
      ],
      "event": {
        "name": "Eintracht Frankfurt - Liverpool",
        "description": "Eintracht Frankfurt - Liverpool el miércoles, 22 de octubre de 2025 a las 21:00",
        "startDate": "2025-10-22T19:00:00",
        "duration": "T1H45M"
      },
      "eventType": "match"
    },
    {
      "sport": "futbol",
      "date": {
        "hour": "21:00",
        "day": "22/10/2025",
        "zone": "Europe/Madrid"
      },
      "details": {
        "competition": "Champions League",
        "round": "Fase Liga"
      },
      "teams": {
        "local": {
          "name": "Atalanta",
          "image": "https://static.futbolenlatv.com/img/20121219034958_atalanta.webp"
        },
        "visitor": {
          "name": "Slavia Praha",
          "image": "https://static.futbolenlatv.com/img/20140822072150-slavia-praga.webp"
        }
      },
      "channels": [
        "M+ Liga de Campeones 4",
        "M+ Liga de Campeones 9"
      ],
      "event": {
        "name": "Atalanta - Slavia Praha",
        "description": "Atalanta - Slavia Praha el miércoles, 22 de octubre de 2025 a las 21:00",
        "startDate": "2025-10-22T19:00:00",
        "duration": "T1H45M"
      },
      "eventType": "match"
    },
    {
      "sport": "futbol",
      "date": {
        "hour": "21:00",
        "day": "22/10/2025",
        "zone": "Europe/Madrid"
      },
      "details": {
        "competition": "Champions League",
        "round": "Fase Liga"
      },
      "teams": {
        "local": {
          "name": "Sporting CP",
          "image": "https://static.futbolenlatv.com/img/20121220121058_sporting-clube-de-portugal.webp"
        },
        "visitor": {
          "name": "O. Marseille",
          "image": "https://static.futbolenlatv.com/img/20130117033826_olympique-de-marseille.webp"
        }
      },
      "channels": [
        "M+ Liga de Campeones 4",
        "M+ Liga de Campeones 8"
      ],
      "event": {
        "name": "Sporting CP - O. Marseille",
        "description": "Sporting CP - O. Marseille el miércoles, 22 de octubre de 2025 a las 21:00",
        "startDate": "2025-10-22T19:00:00",
        "duration": "T1H45M"
      },
      "eventType": "match"
    },
    {
      "sport": "futbol",
      "date": {
        "hour": "21:00",
        "day": "22/10/2025",
        "zone": "Europe/Madrid"
      },
      "details": {
        "competition": "Champions League",
        "round": "Fase Liga"
      },
      "teams": {
        "local": {
          "name": "AS Monaco",
          "image": "https://static.futbolenlatv.com/img/20240923180846-monaco.webp"
        },
        "visitor": {
          "name": "Tottenham",
          "image": "https://static.futbolenlatv.com/img/20200413194326-tottenham.webp"
        }
      },
      "channels": [
        "M+ Liga de Campeones 4",
        "M+ Liga de Campeones 7"
      ],
      "event": {
        "name": "AS Monaco - Tottenham",
        "description": "AS Monaco - Tottenham el miércoles, 22 de octubre de 2025 a las 21:00",
        "startDate": "2025-10-22T19:00:00",
        "duration": "T1H45M"
      },
      "eventType": "match"
    },
    {
      "sport": "futbol",
      "date": {
        "hour": "21:00",
        "day": "22/10/2025",
        "zone": "Europe/Madrid"
      },
      "details": {
        "competition": "FIFA Mundial Femenino Sub-17",
        "round": "Fase de grupos"
      },
      "teams": {
        "local": {
          "name": "Nigeria",
          "image": "https://static.futbolenlatv.com/img/20130103114959_nigeria.webp"
        },
        "visitor": {
          "name": "Francia",
          "image": "https://static.futbolenlatv.com/img/20130124053558_francia.webp"
        }
      },
      "channels": [
        "FIFA+"
      ],
      "event": {
        "name": "Nigeria - Francia",
        "description": "Nigeria - Francia el miércoles, 22 de octubre de 2025 a las 21:00",
        "startDate": "2025-10-22T19:00:00",
        "duration": "T1H45M"
      },
      "eventType": "match"
    },
    {
      "sport": "futbol",
      "date": {
        "hour": "21:00",
        "day": "22/10/2025",
        "zone": "Europe/Madrid"
      },
      "details": {
        "competition": "FIFA Mundial Femenino Sub-17",
        "round": "Fase de grupos"
      },
      "teams": {
        "local": {
          "name": "Costa de Marfil",
          "image": "https://static.futbolenlatv.com/img/20130103113744_cosa-de-marfil.webp"
        },
        "visitor": {
          "name": "Colombia",
          "image": "https://static.futbolenlatv.com/img/20130410092520_colombia.webp"
        }
      },
      "channels": [
        "FIFA+"
      ],
      "event": {
        "name": "Costa de Marfil - Colombia",
        "description": "Costa de Marfil - Colombia el miércoles, 22 de octubre de 2025 a las 21:00",
        "startDate": "2025-10-22T19:00:00",
        "duration": "T1H45M"
      },
      "eventType": "match"
    },
    {
      "sport": "futbol",
      "date": {
        "hour": "21:00",
        "day": "22/10/2025",
        "zone": "Europe/Madrid"
      },
      "details": {
        "competition": "FIFA Mundial Femenino Sub-17",
        "round": "Fase de grupos"
      },
      "teams": {
        "local": {
          "name": "Paraguay",
          "image": "https://static.futbolenlatv.com/img/20130319095210_paraguay.webp"
        },
        "visitor": {
          "name": "Nueva Zelanda",
          "image": "https://static.futbolenlatv.com/img/20130523095300_nueva-zelanda.webp"
        }
      },
      "channels": [
        "FIFA+"
      ],
      "event": {
        "name": "Paraguay - Nueva Zelanda",
        "description": "Paraguay - Nueva Zelanda el miércoles, 22 de octubre de 2025 a las 21:00",
        "startDate": "2025-10-22T19:00:00",
        "duration": "T1H45M"
      },
      "eventType": "match"
    },
    {
      "sport": "futbol",
      "date": {
        "hour": "22:00",
        "day": "22/10/2025",
        "zone": "Europe/Madrid"
      },
      "details": {
        "competition": "Liga Pro Serie B",
        "round": null
      },
      "teams": {
        "local": {
          "name": "Chacaritas FC",
          "image": "https://static.futbolenlatv.com/img/20200918182419-chacaritas-fc.webp"
        },
        "visitor": {
          "name": "CSD Vargas Torres",
          "image": "https://static.futbolenlatv.com/img/20220427095644-csd-vargas-torres.webp"
        }
      },
      "channels": [
        "ElCanalDelFutbol.com"
      ],
      "event": {
        "name": "Chacaritas FC - CSD Vargas Torres",
        "description": "Chacaritas FC - CSD Vargas Torres el miércoles, 22 de octubre de 2025 a las 22:00",
        "startDate": "2025-10-22T20:00:00",
        "duration": "T1H45M"
      },
      "eventType": "match"
    },
    {
      "sport": "futbol",
      "date": {
        "hour": "22:00",
        "day": "22/10/2025",
        "zone": "Europe/Madrid"
      },
      "details": {
        "competition": "Liga Pro Serie B",
        "round": null
      },
      "teams": {
        "local": {
          "name": "Cumbayá FC",
          "image": "https://static.futbolenlatv.com/img/20201120214216-cumbaya-fc.webp"
        },
        "visitor": {
          "name": "Atlético Vinotinto",
          "image": "https://static.futbolenlatv.com/img/20250704101323-atletico-vinotinto.webp"
        }
      },
      "channels": [
        "ElCanalDelFutbol.com"
      ],
      "event": {
        "name": "Cumbayá FC - Atlético Vinotinto",
        "description": "Cumbayá FC - Atlético Vinotinto el miércoles, 22 de octubre de 2025 a las 22:00",
        "startDate": "2025-10-22T20:00:00",
        "duration": "T1H45M"
      },
      "eventType": "match"
    }
  ],
  "updated": "2025-10-21T22:30:01.105Z"
}